spedReader/__init__.py
spedReader/reader.py
spedReader/sped.py
spedreader-0.1.5.dist-info/licenses/LICENSE
spedreader-0.1.5.dist-info/METADATA
spedreader-0.1.5.dist-info/WHEEL
spedreader-0.1.5.dist-info/top_level.txt
spedreader-0.1.5.dist-info/RECORD
