Metadata-Version: 2.4
Name: spedReader
Version: 0.1.5
Summary: Leitor de arquivos SPED brasileiros.
Author-email: Marcus Carpenter <marcus.carpenter@tributodevido.com.br>
Classifier: Programming Language :: Python :: 3
Classifier: License :: OSI Approved :: MIT License
Classifier: Operating System :: OS Independent
Requires-Python: >=3.13
License-File: LICENSE
Requires-Dist: pandas
Dynamic: license-file
